odoo/addons/energy_communities_cooperator/__init__.py
odoo/addons/energy_communities_cooperator/__manifest__.py
odoo/addons/energy_communities_cooperator/controllers/__init__.py
odoo/addons/energy_communities_cooperator/controllers/controllers.py
odoo/addons/energy_communities_cooperator/controllers/website_subscription_main.py
odoo/addons/energy_communities_cooperator/controllers/website_subscription_voluntary_share.py
odoo/addons/energy_communities_cooperator/data/ir_config_parameter_data.xml
odoo/addons/energy_communities_cooperator/data/mail_template_data.xml
odoo/addons/energy_communities_cooperator/data/mail_template_update_data.xml
odoo/addons/energy_communities_cooperator/data/product_data.xml
odoo/addons/energy_communities_cooperator/data/res_users_role_data.xml
odoo/addons/energy_communities_cooperator/demo/res_company_demo.xml
odoo/addons/energy_communities_cooperator/demo/res_user_demo.xml
odoo/addons/energy_communities_cooperator/demo/subscription_request_demo.xml
odoo/addons/energy_communities_cooperator/i18n/ca_ES.po
odoo/addons/energy_communities_cooperator/i18n/es.po
odoo/addons/energy_communities_cooperator/i18n/eu_ES.po
odoo/addons/energy_communities_cooperator/i18n_extra/ca_ES.po
odoo/addons/energy_communities_cooperator/i18n_extra/es.po
odoo/addons/energy_communities_cooperator/i18n_extra/eu_ES.po
odoo/addons/energy_communities_cooperator/models/__init__.py
odoo/addons/energy_communities_cooperator/models/account_move.py
odoo/addons/energy_communities_cooperator/models/account_move_line.py
odoo/addons/energy_communities_cooperator/models/cooperative_membership.py
odoo/addons/energy_communities_cooperator/models/partner.py
odoo/addons/energy_communities_cooperator/models/product.py
odoo/addons/energy_communities_cooperator/models/res_company.py
odoo/addons/energy_communities_cooperator/models/share_line.py
odoo/addons/energy_communities_cooperator/models/subscription_request.py
odoo14_addon_energy_communities_cooperator-14.0.1.2.3.dist-info/METADATA
odoo14_addon_energy_communities_cooperator-14.0.1.2.3.dist-info/WHEEL
odoo14_addon_energy_communities_cooperator-14.0.1.2.3.dist-info/top_level.txt
odoo14_addon_energy_communities_cooperator-14.0.1.2.3.dist-info/RECORD
