Metadata-Version: 2.1
Name: odoo14-addon-energy-communities-cooperator
Version: 14.0.1.2.3
Summary: Energy communities cooperative membership management
Home-page: https://coopdevs.org
Author: Som Comunitats SCCL
License: AGPL-3
Classifier: Programming Language :: Python
Classifier: Framework :: Odoo
Classifier: Framework :: Odoo :: 14.0
Classifier: License :: OSI Approved :: GNU Affero General Public License v3
Requires-Python: >=3.6
Requires-Dist: odoo14-addon-account-multicompany-easy-creation >=14.0.1.0.1.dev2
Requires-Dist: odoo14-addon-cooperator-account-banking-mandate ==14.0.1.1.1
Requires-Dist: odoo14-addon-cooperator-account-payment ==14.0.1.1.0
Requires-Dist: odoo14-addon-cooperator ==14.0.2.1.1
Requires-Dist: odoo14-addon-energy-communities >=14.0.9.0.0
Requires-Dist: odoo14-addon-l10n-es-cooperator ==14.0.0.1.1
Requires-Dist: odoo <14.1dev,>=14.0a
